README.rst
setup.py
gaa/__init__.py
gaa/__main__.py
gaa/cli.py
gaa.egg-info/PKG-INFO
gaa.egg-info/SOURCES.txt
gaa.egg-info/dependency_links.txt
gaa.egg-info/entry_points.txt
gaa.egg-info/top_level.txt