Metadata-Version: 1.1
Name: gaa
Version: 0.1.0
Summary: Genomic Ancestry Analyzer
Home-page: https://github.com/raonyguimaraes/gaa
Author: Raony Guimaraes
Author-email: raonyguimaraes@gmail.com
License: UNKNOWN
Keywords: gaa
Platform: UNKNOWN
Classifier: Programming Language :: Python :: 2.7
Classifier: Programming Language :: Python :: 3.6
